grai_client/__init__.py
grai_client/authentication.py
grai_client/endpoints/__init__.py
grai_client/endpoints/client.py
grai_client/endpoints/rest.py
grai_client/endpoints/utilities.py
grai_client/endpoints/v1/__init__.py
grai_client/endpoints/v1/client.py
grai_client/endpoints/v1/delete.py
grai_client/endpoints/v1/get/__init__.py
grai_client/endpoints/v1/get/edge.py
grai_client/endpoints/v1/get/node.py
grai_client/endpoints/v1/get/organisation.py
grai_client/endpoints/v1/get/source.py
grai_client/endpoints/v1/get/utils.py
grai_client/endpoints/v1/get/workspace.py
grai_client/endpoints/v1/get.py
grai_client/endpoints/v1/patch.py
grai_client/endpoints/v1/post.py
grai_client/endpoints/v1/url.py
grai_client/endpoints/v1/utils.py
grai_client/errors.py
grai_client/integrations/__init__.py
grai_client/integrations/base.py
grai_client/py.typed
grai_client/schemas/__init__.py
grai_client/schemas/labels.py
grai_client/schemas/schema.py
grai_client/testing/__init__.py
grai_client/testing/schema.py
grai_client/update.py
grai_client/utilities/__init__.py
grai_client/utilities/tests.py
grai_client-0.3.5.dist-info/METADATA
grai_client-0.3.5.dist-info/WHEEL
grai_client-0.3.5.dist-info/RECORD
